<?xml version="1.0" encoding="UTF-8"?>
<?xml-stylesheet type="text/xsl" href="../../xslt/summary_report.xsl"?>
<benchResults>
    <benchSummary name="Sample Search Workload" version="0.3">
        <runId>174</runId>
        <startTime>Thu May 21 00:03:48 UTC 2020</startTime>
        <endTime>Thu May 21 00:24:48 UTC 2020</endTime>
        <metric unit="ops/sec">2.002</metric>
        <passed>true</passed>
    </benchSummary>
    <driverSummary name="SearchDriver">
        <metric unit="ops/sec">2.002</metric>
        <startTime>Thu May 21 00:03:48 UTC 2020</startTime>
        <endTime>Thu May 21 00:24:48 UTC 2020</endTime>
        <totalOps unit="operations">2402</totalOps>
        <users>2</users>
        <rtXtps>1.9984</rtXtps>
        <passed>true</passed>
        <mix allowedDeviation="0.0000">
            <operation name="GET">
                <successes>2402</successes>
                <failures>0</failures>
                <mix>1.0000</mix>
                <requiredMix>1.0000</requiredMix>
                <passed>true</passed>
            </operation>
        </mix>
        <responseTimes unit="seconds">
            <operation name="GET" r90th="0.500">
                <avg>0.196</avg>
                <max>0.763</max>
                <sd>0.111</sd>
                <p90th>0.350</p90th>
                <passed>true</passed>
                <p99th>0.523</p99th>
            </operation>
        </responseTimes>
        <delayTimes>
            <operation name="GET" type="cycleTime">
                <targetedAvg>1.000</targetedAvg>
                <actualAvg>0.999</actualAvg>
                <min>0.999</min>
                <max>1.073</max>
                <passed>true</passed>
            </operation>
        </delayTimes>
    </driverSummary>
</benchResults>
